omron-sysmac-simulator/__init__.py
omron-sysmac-simulator/sysmac_simulator.py
omron_sysmac_simulator/__init__.py
omron_sysmac_simulator/sysmac_simulator.py
omron_sysmac_simulator-0.1.4.dist-info/licenses/LICENSE
omron_sysmac_simulator-0.1.4.dist-info/METADATA
omron_sysmac_simulator-0.1.4.dist-info/WHEEL
omron_sysmac_simulator-0.1.4.dist-info/top_level.txt
omron_sysmac_simulator-0.1.4.dist-info/RECORD
