Metadata-Version: 2.4
Name: omron-sysmac-simulator
Version: 0.1.4
Summary: A library to communicate with Omron Sysmac Simulator
Home-page: https://github.com/aphyt/omron_sysmac_simulator
Author: Joseph Ryan
Author-email: jr@aphyt.com
Classifier: Programming Language :: Python :: 3
Classifier: License :: OSI Approved :: GNU General Public License v3 (GPLv3)
Classifier: Operating System :: OS Independent
Requires-Python: >=3.8
License-File: LICENSE
Dynamic: author
Dynamic: author-email
Dynamic: classifier
Dynamic: description
Dynamic: description-content-type
Dynamic: home-page
Dynamic: license-file
Dynamic: requires-python
Dynamic: summary
